titiler/application/__init__.py
titiler/application/main.py
titiler/application/py.typed
titiler/application/settings.py
titiler/application/templates/conformance.html
titiler/application/templates/header.html
titiler/application/templates/landing.html
titiler_application-1.0.2.dist-info/METADATA
titiler_application-1.0.2.dist-info/WHEEL
titiler_application-1.0.2.dist-info/licenses/LICENSE
titiler_application-1.0.2.dist-info/RECORD
